{
  "id": "a1cbb7c3-6e6f-4a22-8c4c-52b4cfd8c3ce",
  "name": "Social Network Local",
  "values": [
    {
      "key": "baseUrl",
      "value": "http://localhost:8080",
      "type": "default",
      "enabled": true
    },
    {
      "key": "emailA",
      "value": "usera@example.com",
      "type": "default",
      "enabled": true
    },
    {
      "key": "passwordA",
      "value": "passwordA123",
      "type": "default",
      "enabled": true
    },
    {
      "key": "firstNameA",
      "value": "User",
      "type": "default",
      "enabled": true
    },
    {
      "key": "lastNameA",
      "value": "Alpha",
      "type": "default",
      "enabled": true
    },
    {
      "key": "dateOfBirthA",
      "value": "01/01/2000",
      "type": "default",
      "enabled": true
    },
    {
      "key": "nicknameA",
      "value": "alpha",
      "type": "default",
      "enabled": true
    },
    {
      "key": "aboutA",
      "value": "User A",
      "type": "default",
      "enabled": true
    },
    {
      "key": "emailB",
      "value": "userb@example.com",
      "type": "default",
      "enabled": true
    },
    {
      "key": "passwordB",
      "value": "passwordB123",
      "type": "default",
      "enabled": true
    },
    {
      "key": "firstNameB",
      "value": "User",
      "type": "default",
      "enabled": true
    },
    {
      "key": "lastNameB",
      "value": "Beta",
      "type": "default",
      "enabled": true
    },
    {
      "key": "dateOfBirthB",
      "value": "02/02/2001",
      "type": "default",
      "enabled": true
    },
    {
      "key": "nicknameB",
      "value": "beta",
      "type": "default",
      "enabled": true
    },
    {
      "key": "aboutB",
      "value": "User B",
      "type": "default",
      "enabled": true
    },
    {
      "key": "targetId",
      "value": 2,
      "type": "default",
      "enabled": true
    },
    {
      "key": "requestId",
      "value": 1,
      "type": "default",
      "enabled": true
    },
    {
      "key": "profileId",
      "value": 2,
      "type": "default",
      "enabled": true
    },
    {
      "key": "isPublic",
      "value": true,
      "type": "default",
      "enabled": true
    }
  ],
  "_postman_variable_scope": "environment",
  "_postman_exported_at": "2025-01-24T00:00:00Z",
  "_postman_exported_using": "Postman/10.x"
}
